snap_studio/__init__.py
snap_studio/app.py
snap_studio/cli.py
snap_studio/bin/__init__.py
snap_studio/bin/snap-studio
snap_studio/static/index.html
snap_studio/static/index.js
snap_studio-0.0.3.data/scripts/snap-studio
snap_studio-0.0.3.dist-info/DESCRIPTION.rst
snap_studio-0.0.3.dist-info/METADATA
snap_studio-0.0.3.dist-info/RECORD
snap_studio-0.0.3.dist-info/WHEEL
snap_studio-0.0.3.dist-info/metadata.json
snap_studio-0.0.3.dist-info/top_level.txt
