Metadata-Version: 2.0
Name: snap-studio
Version: 0.0.3
Summary: SparklineData SNAP Studio
Home-page: https://gitlab.com/SparklineData/Public/snap-studio
Author: Ali Rathore
Author-email: ali1rathore@gmail.com
License: GNU General Public License v3
Keywords: snap_studio
Platform: UNKNOWN
Classifier: Development Status :: 2 - Pre-Alpha
Classifier: Intended Audience :: Developers
Classifier: License :: OSI Approved :: GNU General Public License v3 (GPLv3)
Classifier: Natural Language :: English
Classifier: Programming Language :: Python :: 3
Classifier: Programming Language :: Python :: 3.3
Classifier: Programming Language :: Python :: 3.4
Classifier: Programming Language :: Python :: 3.5
Requires-Dist: Flask (==0.12.2)
Requires-Dist: Flask-Script (==2.0.3)
Requires-Dist: Jinja2 (==2.10)
Requires-Dist: MarkupSafe (==1.0)
Requires-Dist: PyHive (==0.5.0)
Requires-Dist: Werkzeug (==0.13)
Requires-Dist: click (==6.7)
Requires-Dist: flask-cors (==3.0.3)
Requires-Dist: gunicorn (==19.7.1)
Requires-Dist: itsdangerous (==0.24)
Requires-Dist: sasl (==0.2.1)
Requires-Dist: thrift (==0.10.0)
Requires-Dist: thrift-sasl (==0.3.0)
